{
    "ads_time": 0.52,
    "capacity": [
        5,
        1
    ],
    "class": "SR",
    "damages": {
        "0": 0,
        "1": 0,
        "2": 0,
        "3": 0,
        "4": 0,
        "5": 135,
        "6": 0,
        "7": 0,
        "8": 0,
        "9": 0,
        "10": 0,
        "11": 0,
        "12": 0,
        "13": 0,
        "14": 0,
        "15": 0,
        "16": 0,
        "17": 0,
        "18": 0,
        "19": 0,
        "20": 0,
        "21": 0,
        "22": 0,
        "23": 0,
        "24": 0,
        "25": 0,
        "26": 0,
        "27": 0,
        "28": 0,
        "29": 135,
        "30": 134,
        "31": 131,
        "32": 128,
        "33": 125,
        "34": 123,
        "35": 120,
        "36": 117,
        "37": 115,
        "38": 112,
        "39": 109,
        "40": 109
    },
    "extended_barrel": false,
    "extra_ammo": 30,
    "has_grip": false,
    "has_laser": false,
    "name": "CSRX 300",
    "pellets": 1,
    "reload_times": [
        null,
        null
    ],
    "rpm": 50
}